image_toolbox/__init__.py
image_toolbox/basic_transform/__init__.py
image_toolbox/basic_transform/basic.py
image_toolbox/encoding/__init__.py
image_toolbox/encoding/base64.py
image_toolbox/io/__init__.py
image_toolbox/io/io.py
image_toolbox/miscellaneous/__init__.py
image_toolbox/miscellaneous/np_utils.py
image_toolbox/miscellaneous/utils.py
image_toolbox/miscellaneous/iterator/__init__.py
image_toolbox/miscellaneous/iterator/iterator.py
image_toolbox/preprocessing/__init__.py
image_toolbox/preprocessing/preprocessing.py
image_toolbox/tests/__init__.py
image_toolbox/tests/test_encoding.py
image_toolbox/tests/test_io.py
image_toolbox/tests/test_miscellaneous.py
image_toolbox/transform/__init__.py
image_toolbox_glaiel-0.0.0.dist-info/LICENSE
image_toolbox_glaiel-0.0.0.dist-info/METADATA
image_toolbox_glaiel-0.0.0.dist-info/WHEEL
image_toolbox_glaiel-0.0.0.dist-info/top_level.txt
image_toolbox_glaiel-0.0.0.dist-info/RECORD
